TemplateScanner/scanner.py
cloudconformity-0.1.9.dist-info/LICENSE
cloudconformity-0.1.9.dist-info/METADATA
cloudconformity-0.1.9.dist-info/WHEEL
cloudconformity-0.1.9.dist-info/entry_points.txt
cloudconformity-0.1.9.dist-info/top_level.txt
cloudconformity-0.1.9.dist-info/RECORD
