Metadata-Version: 2.1
Name: cloudconformity
Version: 0.1.9
Summary: Cloud Conformity template scanner tool
Home-page: https://github.com/JustinDPerkins/cloudconformity
Author: Justin Perkins
Author-email: justin_perkins@trendmicro.com
License: UNKNOWN
Platform: UNKNOWN
Classifier: Programming Language :: Python :: 3
Classifier: License :: OSI Approved :: MIT License
Requires-Python: >=3.6
Requires-Dist: requests
